setup.py
prct_distributions/Binomialdistribution.py
prct_distributions/Gaussiandistribution.py
prct_distributions/Generaldistribution.py
prct_distributions/__init__.py
prct_distributions.egg-info/PKG-INFO
prct_distributions.egg-info/SOURCES.txt
prct_distributions.egg-info/dependency_links.txt
prct_distributions.egg-info/not-zip-safe
prct_distributions.egg-info/top_level.txt