Metadata-Version: 1.0
Name: prct-distributions
Version: 1.0
Summary: Gaussian distributions
Home-page: UNKNOWN
Author: siva kumar pabbisetty
Author-email: pabbisettyssivakumar@gmail.com
License: UNKNOWN
Platform: UNKNOWN
